wynn/__init__.py
wynn/guild.py
wynn/ingredient.py
wynn/item.py
wynn/leaderboard.py
wynn/network.py
wynn/player.py
wynn/recipe.py
wynn/requests.py
wynn/search.py
wynn/territory.py
wynn.py-0.1.0.dist-info/LICENSE
wynn.py-0.1.0.dist-info/METADATA
wynn.py-0.1.0.dist-info/WHEEL
wynn.py-0.1.0.dist-info/top_level.txt
wynn.py-0.1.0.dist-info/RECORD
