Metadata-Version: 2.1
Name: wynn.py
Version: 0.1.0
Summary: A Python wrapper for the Wynncraft public API
Home-page: https://github.com/Zakru/wynn.py
Author: Zakru
License: UNKNOWN
Project-URL: Documentation, https://wynnpy.readthedocs.io/en/stable/
Project-URL: Source Code, https://github.com/Zakru/wynn.py
Project-URL: Issue Tracker, https://github.com/Zakru/wynn.py/issues
Platform: UNKNOWN
Classifier: Development Status :: 3 - Alpha
Classifier: Intended Audience :: Developers
Classifier: License :: OSI Approved :: MIT License
Classifier: Operating System :: OS Independent
Classifier: Programming Language :: Python :: 3
Classifier: Topic :: Games/Entertainment
Classifier: Topic :: Software Development :: Libraries
Provides-Extra: docs
Requires-Dist: sphinx (~=2.2) ; extra == 'docs'
Requires-Dist: sphinx-rtd-theme (~=0.4) ; extra == 'docs'
